vodiboi_state_space_visualizer/__init__.py
vodiboi_state_space_visualizer/games/__init__.py
vodiboi_state_space_visualizer/games/aztec_diamond.py
vodiboi_state_space_visualizer/games/game.py
vodiboi_state_space_visualizer/games/game_2048.py
vodiboi_state_space_visualizer/games/graph.py
vodiboi_state_space_visualizer/games/klotski.py
vodiboi_state_space_visualizer/games/sliding_block_puzzle.py
vodiboi_state_space_visualizer/games/snake.py
vodiboi_state_space_visualizer/games/towers_of_hanoi.py
vodiboi_state_space_visualizer/visualizers/__init__.py
vodiboi_state_space_visualizer/visualizers/flet_visualizer.py
vodiboi_state_space_visualizer/visualizers/jupyter_visualizer.py
vodiboi_state_space_visualizer-0.1.6.dist-info/licenses/LICENSE
vodiboi_state_space_visualizer-0.1.6.dist-info/METADATA
vodiboi_state_space_visualizer-0.1.6.dist-info/WHEEL
vodiboi_state_space_visualizer-0.1.6.dist-info/top_level.txt
vodiboi_state_space_visualizer-0.1.6.dist-info/RECORD
