Metadata-Version: 2.4
Name: vodiboi_state_space_visualizer
Version: 0.1.6
Summary: A state space visualizing tool
Author-email: Aayan Arish <aayan@arish.com>
License-Expression: MIT
Project-URL: Homepage, https://test.pypi.org/project/vodiboi-state-space-visualizer/
Classifier: Programming Language :: Python :: 3
Classifier: Operating System :: OS Independent
Requires-Python: >=3.9
License-File: LICENSE
Requires-Dist: flet
Requires-Dist: numpy
Requires-Dist: networkx
Requires-Dist: plotly
Dynamic: license-file
